<?xml version="1.0"?>
<edgarSubmission>

    <schemaVersion>X0707</schemaVersion>

    <submissionType>D</submissionType>

    <testOrLive>LIVE</testOrLive>

    <primaryIssuer>
        <cik>0001610409</cik>
        <entityName>Green Wave Fertilizer, LLC</entityName>
        <issuerAddress>
            <street1>17208 REDHILL</street1>
            <city>IRVINE</city>
            <stateOrCountry>CA</stateOrCountry>
            <stateOrCountryDescription>CALIFORNIA</stateOrCountryDescription>
            <zipCode>92614</zipCode>
        </issuerAddress>
        <issuerPhoneNumber>(949) 230-1035</issuerPhoneNumber>
        <jurisdictionOfInc>CALIFORNIA</jurisdictionOfInc>
        <issuerPreviousNameList>
            <value>None</value>
        </issuerPreviousNameList>
        <edgarPreviousNameList>
            <value>None</value>
        </edgarPreviousNameList>
        <entityType>Limited Liability Company</entityType>
        <yearOfInc>
            <withinFiveYears>true</withinFiveYears>
            <value>2011</value>
        </yearOfInc>
    </primaryIssuer>

    <relatedPersonsList>
        <relatedPersonInfo>
            <relatedPersonName>
                <firstName>Robert</firstName>
                <lastName>Reese</lastName>
            </relatedPersonName>
            <relatedPersonAddress>
                <street1>17208 Redhill</street1>
                <city>Irvine</city>
                <stateOrCountry>CA</stateOrCountry>
                <stateOrCountryDescription>CALIFORNIA</stateOrCountryDescription>
                <zipCode>92614</zipCode>
            </relatedPersonAddress>
            <relatedPersonRelationshipList>
                <relationship>Executive Officer</relationship>
            </relatedPersonRelationshipList>
            <relationshipClarification></relationshipClarification>
        </relatedPersonInfo>
        <relatedPersonInfo>
            <relatedPersonName>
                <firstName>Thomas</firstName>
                <lastName>Price</lastName>
            </relatedPersonName>
            <relatedPersonAddress>
                <street1>17208 Redhill</street1>
                <city>Irvine</city>
                <stateOrCountry>CA</stateOrCountry>
                <stateOrCountryDescription>CALIFORNIA</stateOrCountryDescription>
                <zipCode>92614</zipCode>
            </relatedPersonAddress>
            <relatedPersonRelationshipList>
                <relationship>Executive Officer</relationship>
            </relatedPersonRelationshipList>
            <relationshipClarification></relationshipClarification>
        </relatedPersonInfo>
    </relatedPersonsList>

    <offeringData>
        <industryGroup>
            <industryGroupType>Other</industryGroupType>
        </industryGroup>
        <issuerSize>
            <revenueRange>No Revenues</revenueRange>
        </issuerSize>
        <federalExemptionsExclusions>
            <item>06b</item>
        </federalExemptionsExclusions>
        <typeOfFiling>
            <newOrAmendment>
                <isAmendment>false</isAmendment>
            </newOrAmendment>
            <dateOfFirstSale>
                <value>2014-05-29</value>
            </dateOfFirstSale>
        </typeOfFiling>
        <durationOfOffering>
            <moreThanOneYear>false</moreThanOneYear>
        </durationOfOffering>
        <typesOfSecuritiesOffered>
            <isDebtType>true</isDebtType>
        </typesOfSecuritiesOffered>
        <businessCombinationTransaction>
            <isBusinessCombinationTransaction>false</isBusinessCombinationTransaction>
            <clarificationOfResponse></clarificationOfResponse>
        </businessCombinationTransaction>
        <minimumInvestmentAccepted>10000</minimumInvestmentAccepted>
        <salesCompensationList></salesCompensationList>
        <offeringSalesAmounts>
            <totalOfferingAmount>Indefinite</totalOfferingAmount>
            <totalAmountSold>300000</totalAmountSold>
            <totalRemaining>Indefinite</totalRemaining>
            <clarificationOfResponse></clarificationOfResponse>
        </offeringSalesAmounts>
        <investors>
            <hasNonAccreditedInvestors>false</hasNonAccreditedInvestors>
            <totalNumberAlreadyInvested>2</totalNumberAlreadyInvested>
        </investors>
        <salesCommissionsFindersFees>
            <salesCommissions>
                <dollarAmount>0</dollarAmount>
            </salesCommissions>
            <findersFees>
                <dollarAmount>0</dollarAmount>
            </findersFees>
            <clarificationOfResponse></clarificationOfResponse>
        </salesCommissionsFindersFees>
        <useOfProceeds>
            <grossProceedsUsed>
                <dollarAmount>0</dollarAmount>
            </grossProceedsUsed>
            <clarificationOfResponse></clarificationOfResponse>
        </useOfProceeds>
        <signatureBlock>
            <authorizedRepresentative>false</authorizedRepresentative>
            <signature>
                <issuerName>Green Wave Fertilizer, LLC</issuerName>
                <signatureName>/s/ Stephen Reese</signatureName>
                <nameOfSigner>Stephen Reese</nameOfSigner>
                <signatureTitle>Authorized Officer</signatureTitle>
                <signatureDate>2014-06-10</signatureDate>
            </signature>
        </signatureBlock>
    </offeringData>
</edgarSubmission>
