<?xml version="1.0"?>
<edgarSubmission>

    <schemaVersion>X0708</schemaVersion>

    <submissionType>D</submissionType>

    <testOrLive>LIVE</testOrLive>

    <primaryIssuer>
        <cik>0001829412</cik>
        <entityName>QCode Media, Inc.</entityName>
        <issuerAddress>
            <street1>6902 SANTA MONICA BLVD.</street1>
            <city>LOS ANGELES</city>
            <stateOrCountry>CA</stateOrCountry>
            <stateOrCountryDescription>CALIFORNIA</stateOrCountryDescription>
            <zipCode>90038</zipCode>
        </issuerAddress>
        <issuerPhoneNumber>323-916-5030</issuerPhoneNumber>
        <jurisdictionOfInc>DELAWARE</jurisdictionOfInc>
        <issuerPreviousNameList>
            <previousName>QCode Media, LLC</previousName>
        </issuerPreviousNameList>
        <edgarPreviousNameList>
            <value>None</value>
        </edgarPreviousNameList>
        <entityType>Corporation</entityType>
        <yearOfInc>
            <withinFiveYears>true</withinFiveYears>
            <value>2019</value>
        </yearOfInc>
    </primaryIssuer>

    <relatedPersonsList>
        <relatedPersonInfo>
            <relatedPersonName>
                <firstName>Rob</firstName>
                <lastName>Herting</lastName>
            </relatedPersonName>
            <relatedPersonAddress>
                <street1>6902 Santa Monica Blvd.</street1>
                <city>LOS ANGELES</city>
                <stateOrCountry>CA</stateOrCountry>
                <stateOrCountryDescription>CALIFORNIA</stateOrCountryDescription>
                <zipCode>90038</zipCode>
            </relatedPersonAddress>
            <relatedPersonRelationshipList>
                <relationship>Executive Officer</relationship>
                <relationship>Director</relationship>
            </relatedPersonRelationshipList>
            <relationshipClarification></relationshipClarification>
        </relatedPersonInfo>
        <relatedPersonInfo>
            <relatedPersonName>
                <firstName>Mark</firstName>
                <lastName>Genender</lastName>
            </relatedPersonName>
            <relatedPersonAddress>
                <street1>6902 Santa Monica Blvd.</street1>
                <city>LOS ANGELES</city>
                <stateOrCountry>CA</stateOrCountry>
                <stateOrCountryDescription>CALIFORNIA</stateOrCountryDescription>
                <zipCode>90038</zipCode>
            </relatedPersonAddress>
            <relatedPersonRelationshipList>
                <relationship>Executive Officer</relationship>
                <relationship>Director</relationship>
            </relatedPersonRelationshipList>
            <relationshipClarification></relationshipClarification>
        </relatedPersonInfo>
        <relatedPersonInfo>
            <relatedPersonName>
                <firstName>Brian</firstName>
                <lastName>Kavanaugh-Jones</lastName>
            </relatedPersonName>
            <relatedPersonAddress>
                <street1>7122 Beverly Blvd, Suite F</street1>
                <city>Los Angeles</city>
                <stateOrCountry>CA</stateOrCountry>
                <stateOrCountryDescription>CALIFORNIA</stateOrCountryDescription>
                <zipCode>90036</zipCode>
            </relatedPersonAddress>
            <relatedPersonRelationshipList>
                <relationship>Executive Officer</relationship>
                <relationship>Director</relationship>
            </relatedPersonRelationshipList>
            <relationshipClarification></relationshipClarification>
        </relatedPersonInfo>
        <relatedPersonInfo>
            <relatedPersonName>
                <firstName>Ryan</firstName>
                <lastName>Taylor</lastName>
            </relatedPersonName>
            <relatedPersonAddress>
                <street1>614 Chapala St.</street1>
                <city>Santa Barbara</city>
                <stateOrCountry>CA</stateOrCountry>
                <stateOrCountryDescription>CALIFORNIA</stateOrCountryDescription>
                <zipCode>93101</zipCode>
            </relatedPersonAddress>
            <relatedPersonRelationshipList>
                <relationship>Director</relationship>
            </relatedPersonRelationshipList>
            <relationshipClarification></relationshipClarification>
        </relatedPersonInfo>
    </relatedPersonsList>

    <offeringData>
        <industryGroup>
            <industryGroupType>Other</industryGroupType>
        </industryGroup>
        <issuerSize>
            <revenueRange>Decline to Disclose</revenueRange>
        </issuerSize>
        <federalExemptionsExclusions>
            <item>06b</item>
        </federalExemptionsExclusions>
        <typeOfFiling>
            <newOrAmendment>
                <isAmendment>false</isAmendment>
            </newOrAmendment>
            <dateOfFirstSale>
                <value>2020-10-09</value>
            </dateOfFirstSale>
        </typeOfFiling>
        <durationOfOffering>
            <moreThanOneYear>false</moreThanOneYear>
        </durationOfOffering>
        <typesOfSecuritiesOffered>
            <isEquityType>true</isEquityType>
        </typesOfSecuritiesOffered>
        <businessCombinationTransaction>
            <isBusinessCombinationTransaction>false</isBusinessCombinationTransaction>
            <clarificationOfResponse></clarificationOfResponse>
        </businessCombinationTransaction>
        <minimumInvestmentAccepted>20000</minimumInvestmentAccepted>
        <salesCompensationList></salesCompensationList>
        <offeringSalesAmounts>
            <totalOfferingAmount>6400010</totalOfferingAmount>
            <totalAmountSold>6400010</totalAmountSold>
            <totalRemaining>0</totalRemaining>
            <clarificationOfResponse></clarificationOfResponse>
        </offeringSalesAmounts>
        <investors>
            <hasNonAccreditedInvestors>false</hasNonAccreditedInvestors>
            <totalNumberAlreadyInvested>11</totalNumberAlreadyInvested>
        </investors>
        <salesCommissionsFindersFees>
            <salesCommissions>
                <dollarAmount>0</dollarAmount>
            </salesCommissions>
            <findersFees>
                <dollarAmount>0</dollarAmount>
            </findersFees>
            <clarificationOfResponse></clarificationOfResponse>
        </salesCommissionsFindersFees>
        <useOfProceeds>
            <grossProceedsUsed>
                <dollarAmount>0</dollarAmount>
            </grossProceedsUsed>
            <clarificationOfResponse></clarificationOfResponse>
        </useOfProceeds>
        <signatureBlock>
            <authorizedRepresentative>false</authorizedRepresentative>
            <signature>
                <issuerName>QCode Media, Inc.</issuerName>
                <signatureName>/s/ Rob Herting</signatureName>
                <nameOfSigner>Rob Herting</nameOfSigner>
                <signatureTitle>President and CEO</signatureTitle>
                <signatureDate>2020-10-22</signatureDate>
            </signature>
        </signatureBlock>
    </offeringData>
</edgarSubmission>
