<?xml version="1.0"?>
<edgarSubmission>

    <schemaVersion>X0603</schemaVersion>

    <submissionType>D</submissionType>

    <testOrLive>LIVE</testOrLive>

    <primaryIssuer>
        <cik>0001485913</cik>
        <entityName>25 Hill Akron Filmworks, LLC</entityName>
        <issuerAddress>
            <street1>12041 MAXWELLTON ROAD</street1>
            <city>STUDIO CITY</city>
            <stateOrCountry>CA</stateOrCountry>
            <zipCode>91604</zipCode>
        </issuerAddress>
        <issuerPhoneNumber>818-754-8977</issuerPhoneNumber>
        <jurisdictionOfInc>OHIO</jurisdictionOfInc>
        <issuerPreviousNameList>
            <value>None</value>
        </issuerPreviousNameList>
        <edgarPreviousNameList>
            <value>None</value>
        </edgarPreviousNameList>
        <entityType>Limited Liability Company</entityType>
        <yearOfInc>
            <withinFiveYears>true</withinFiveYears>
            <value>2009</value>
        </yearOfInc>
    </primaryIssuer>

    <relatedPersonsList>
        <relatedPersonInfo>
            <relatedPersonName>
                <firstName>Corbin</firstName>
                <lastName>Bernsen</lastName>
            </relatedPersonName>
            <relatedPersonAddress>
                <street1>12041 Maxwellton Road</street1>
                <city>Studio City</city>
                <stateOrCountry>CA</stateOrCountry>
                <zipCode>91604</zipCode>
            </relatedPersonAddress>
            <relatedPersonRelationshipList>
                <relationship>Executive Officer</relationship>
            </relatedPersonRelationshipList>
            <relationshipClarification></relationshipClarification>
        </relatedPersonInfo>
    </relatedPersonsList>

    <offeringData>
        <industryGroup>
            <industryGroupType>Other</industryGroupType>
        </industryGroup>
        <issuerSize>
            <revenueRange>No Revenues</revenueRange>
        </issuerSize>
        <federalExemptionsExclusions>
            <item>06</item>
        </federalExemptionsExclusions>
        <typeOfFiling>
            <newOrAmendment>
                <isAmendment>false</isAmendment>
            </newOrAmendment>
            <dateOfFirstSale>
                <value>2010-02-17</value>
            </dateOfFirstSale>
        </typeOfFiling>
        <durationOfOffering>
            <moreThanOneYear>false</moreThanOneYear>
        </durationOfOffering>
        <typesOfSecuritiesOffered>
            <isEquityType>true</isEquityType>
        </typesOfSecuritiesOffered>
        <businessCombinationTransaction>
            <isBusinessCombinationTransaction>false</isBusinessCombinationTransaction>
            <clarificationOfResponse></clarificationOfResponse>
        </businessCombinationTransaction>
        <minimumInvestmentAccepted>25000</minimumInvestmentAccepted>
        <salesCompensationList>
            <recipient>
                <recipientName>Corbin Bernsen</recipientName>
                <recipientCRDNumber>None</recipientCRDNumber>
                <associatedBDName>None</associatedBDName>
                <associatedBDCRDNumber>None</associatedBDCRDNumber>
                <recipientAddress>
                    <street1>12041 Maxwellton Road</street1>
                    <city>Studio City</city>
                    <stateOrCountry>CA</stateOrCountry>
                    <zipCode>91604</zipCode>
                </recipientAddress>
                <statesOfSolicitationList>
                    <value>All States</value>
                </statesOfSolicitationList>
            </recipient>
        </salesCompensationList>
        <offeringSalesAmounts>
            <totalOfferingAmount>1000000</totalOfferingAmount>
            <totalAmountSold>225000</totalAmountSold>
            <totalRemaining>775000</totalRemaining>
            <clarificationOfResponse>The minimum amount of the offering is $500,000.00.  The maximum amount of the offering is $1,000,000.00.</clarificationOfResponse>
        </offeringSalesAmounts>
        <investors>
            <hasNonAccreditedInvestors>false</hasNonAccreditedInvestors>
            <totalNumberAlreadyInvested>9</totalNumberAlreadyInvested>
        </investors>
        <salesCommissionsFindersFees>
            <salesCommissions>
                <dollarAmount>0</dollarAmount>
            </salesCommissions>
            <findersFees>
                <dollarAmount>0</dollarAmount>
            </findersFees>
            <clarificationOfResponse></clarificationOfResponse>
        </salesCommissionsFindersFees>
        <useOfProceeds>
            <grossProceedsUsed>
                <dollarAmount>50000</dollarAmount>
                <isEstimate>true</isEstimate>
            </grossProceedsUsed>
            <clarificationOfResponse>No executive shall be paid compensation, but Managing Member Corbin Bernsen may be paid actor and/or director fees.</clarificationOfResponse>
        </useOfProceeds>
        <signatureBlock>
            <authorizedRepresentative>false</authorizedRepresentative>
            <signature>
                <issuerName>25 Hill Akron Filmworks, LLC</issuerName>
                <signatureName>Corbin Bernsen</signatureName>
                <nameOfSigner>Corbin Bernsen</nameOfSigner>
                <signatureTitle>President</signatureTitle>
                <signatureDate>2010-03-03</signatureDate>
            </signature>
        </signatureBlock>
    </offeringData>
</edgarSubmission>
